{
  "$schema": "http://json-schema.org/draft-07/schema",
  "$id": "http://example.com/databank-resource-metadata.schema.json",
  "type": "object",
  "title": "Data Bank Resource Metadata Schema",
  "description": "The root schema comprises the entire JSON document",
  "default": {},
  "examples": [
    {
      "name": "subdistrict-weather-info",
      "type": [
        "adex:DataBank"
      ],
      "label": "SomeLabel",
      "description": "SomeDescription",
      "shortDescription" : "a short description about the item",
      "tags": ["environment", "weather", "rainfall", "temperature"],
      "provider": "337545aa-1fa5-4ca0-bf3d-072144dec5b6",
      "resourceGroup": "96bc97bf-504e-4306-bb49-99d77896cf1d",
      "resourceServer": "85bc97bf-904f-2306-gb49-89d77896cf2e",
      "accessPolicy": "RESTRICTED",
      "organizationType": "Private",
      "fileFormat": "xlsx",
      "dataReadiness": 80,
      "industry": "Climate Research",
      "uploadedBy": "john.doe@datakaveri.org",
      "geoCoverage": "Pan India",
      "yearRange": "2015-2023",
      "verifiedBy": "Ministry of Earth Sciences",
      "uploadFrequency": "Weekly",
      "license": "CC-BY 4.0",
      "department": "Department of IT, Electronics and Communication",
      "resourceType": "MESSAGESTREAM",
      "adexResourceAPIs": [
        "TEMPORAL",
        "ATTR"
      ],
      "iudxResourceAPIs": [
        "ATTR"
      ],
      "location": {
        "SomeKey": "SomeValue"
      },
      "dataDescriptor": {
        "SomeKey": "SomeValue"
      },
      "dataSample": {
        "SomeKey": "SomeValue",
        "observationDateTime": "2023-02-03T08:30:00+05:30"
      }
    }
  ],
  "required": [
    "name",
    "type",
    "label",
    "shortDescription",
    "description",
    "tags",
    "provider",
    "resourceGroup",
    "resourceServer",
    "accessPolicy",
    "organizationType",
    "fileFormat",
    "dataReadiness",
    "department",
    "resourceType",
    "adexResourceAPIs",
    "iudxResourceAPIs",
    "location",
    "dataDescriptor",
    "dataSample",
    "industry",
    "uploadedBy",
    "geoCoverage",
    "yearRange",
    "verifiedBy",
    "uploadFrequency",
    "license"
  ],
  "properties": {
    "name": {
      "$id": "#/properties/name",
      "type": "string",
      "title": "The name schema",
      "description": "An explanation about the purpose of this instance.",
      "default": "",
      "examples": ["SomePlace"],
      "maxLength": 512,
      "pattern": "^[a-zA-Z0-9]([\\w-]*[a-zA-Z0-9 ])?$"
    },
    "id": {
      "$id": "#/properties/id",
      "type": "string",
      "title": "The id schema",
      "description": "An explanation about the purpose of this instance.",
      "default": "",
      "examples": [
        "8b95ab80-2aaf-4636-a65e-7f2563d0d371"
      ],
      "maxLength": 36,
      "pattern": "^[a-zA-Z0-9]{8}-[a-zA-Z0-9]{4}-[a-zA-Z0-9]{4}-[a-zA-Z0-9]{4}-[a-zA-Z0-9]{12}$"
    },
    "type": {
      "$id": "#/properties/type",
      "type": "array",
      "title": "The type schema",
      "description": "An explanation about the purpose of this instance.",
      "default": [],
      "examples": [
        [
          "adex:DataBank"
        ]
      ],
      "additionalItems": true,
      "items": {
        "$id": "#/properties/type/items",
        "anyOf": [
          {
            "$id": "#/properties/type/items/anyOf/0",
            "type": "string",
            "title": "The first anyOf schema",
            "description": "An explanation about the purpose of this instance.",
            "default": "",
            "examples": [
              "adex:DataBank"
            ]
          }
        ]
      }
    },
    "tags": {
      "$id": "#/properties/tags",
      "type": "array",
      "items": {
        "type": "string"
      },
      "title": "The tags schema",
      "description": "An explanation about the purpose of this instance.",
      "default": ""
    },
    "provider": {
      "$id": "#/properties/provider",
      "type": "string",
      "title": "The provider schema",
      "description": "An explanation about the purpose of this instance.",
      "default": "",
      "examples": ["8b95ab80-2aaf-4636-a65e-7f2563d0d371"],
      "maxLength": 36,
      "pattern": "^[a-zA-Z0-9]{8}-[a-zA-Z0-9]{4}-[a-zA-Z0-9]{4}-[a-zA-Z0-9]{4}-[a-zA-Z0-9]{12}$"
    },
    "resourceGroup": {
      "$id": "#/properties/resourceGroup",
      "type": "string",
      "title": "The resourceGroup schema",
      "description": "An explanation about the purpose of this instance.",
      "default": "",
      "examples": ["8b95ab80-2aaf-4636-a65e-7f2563d0d371"],
      "maxLength": 36,
      "pattern": "^[a-zA-Z0-9]{8}-[a-zA-Z0-9]{4}-[a-zA-Z0-9]{4}-[a-zA-Z0-9]{4}-[a-zA-Z0-9]{12}$"
    },
    "resourceServer": {
      "$id": "#/properties/resourceServer",
      "type": "string",
      "title": "The resourceServer schema",
      "description": "An explanation about the purpose of this instance.",
      "default": "",
      "examples": [
        "8b95ab80-2aaf-4636-a65e-7f2563d0d371"
      ],
      "maxLength": 36,
      "pattern": "^[a-zA-Z0-9]{8}-[a-zA-Z0-9]{4}-[a-zA-Z0-9]{4}-[a-zA-Z0-9]{4}-[a-zA-Z0-9]{12}$"
    },
    "accessPolicy": {
      "$id": "#/properties/accessPolicy",
      "type": "string",
      "title": "The access policy schema",
      "default": "",
      "examples": ["RESTRICTED", "PII"],
      "pattern": "^(RESTRICTED|OPEN|PII|PRIVATE|restricted|open|pii|private)$"
    },
    "label": {
      "type": "string",
      "title": "The label schema",
      "maxLength": 512
    },
    "description": {
      "type": "string",
      "title": "The description schema"
    },
    "organizationType": {
      "type": "string",
      "title": "The organizationType schema"
    },
    "shortDescription": {
      "type": "string",
      "title": ""
    },
    "industry" : {
      "type": "string",
      "title": ""
    },
    "uploadedBy": {
      "type": "string",
      "title": ""
    },
    "geoCoverage": {
      "type": "string",
      "title": ""
    },
    "yearRange": {
      "type": "string",
      "title": ""
    },
    "verifiedBy": {
      "type": "string",
      "title": ""
    },
    "uploadFrequency": {
      "type": "string",
      "title": ""
    },
    "license": {
      "type": "string",
      "title": ""
    },
    "fileFormat": {
      "type": "string",
      "title": "The fileFormat schema"
    },
    "dataReadiness": {
      "type": "integer",
      "title": "The dataReadiness schema",
      "minimum": 0,
      "maximum": 100
    },
    "department": {
      "type": "string",
      "title": "The department schema"
    },
    "resourceType": {
      "type": "string",
      "title": "The resourceType schema",
      "enum": ["MESSAGESTREAM", "STATIC", "API"]
    },
    "adexResourceAPIs": {
      "type": "array",
      "items": {
        "type": "string"
      }
    },
    "iudxResourceAPIs": {
      "type": "array",
      "items": {
        "type": "string"
      }
    },
    "location": {
      "type": "object",
      "title": "The location schema",
      "properties": {
        "type": {
          "type": "string",
          "const": "Place"
        },
        "address": {
          "type": "string"
        },
        "geometry": {
          "type": "object",
          "properties": {
            "type": {
              "type": "string",
              "const": "Polygon"
            },
            "coordinates": {
              "type": "array",
              "items": {
                "type": "array",
                "items": {
                  "type": "array",
                  "items": [
                    { "type": "number" },
                    { "type": "number" }
                  ],
                  "minItems": 2,
                  "maxItems": 2
                },
                "minItems": 4
              }
            }
          },
          "required": ["type", "coordinates"]
        }
      },
      "required": ["type", "address", "geometry"]
    },
    "dataDescriptor": {
      "type": "object",
      "title": "The dataDescriptor schema",
      "description": "Definition of the structure and types of observed data attributes.",
      "properties": {
        "@context": { "type": "string" },
        "type": {
          "type": "array",
          "items": { "type": "string" }
        },
        "dataDescriptorLabel": { "type": "string" },
        "description": { "type": "string" },
        "districtCode": {
          "type": "object",
          "properties": {
            "type": { "type": "array", "items": { "type": "string" } },
            "description": { "type": "string" },
            "dataSchema": { "type": "string" }
          }
        },
        "subDistrictCode": {
          "type": "object",
          "properties": {
            "type": { "type": "array", "items": { "type": "string" } },
            "description": { "type": "string" },
            "dataSchema": { "type": "string" }
          }
        },
        "precipitation": {
          "type": "object",
          "properties": {
            "type": { "type": "array", "items": { "type": "string" } },
            "description": { "type": "string" },
            "unitCode": { "type": "string" },
            "unitText": { "type": "string" },
            "dataSchema": { "type": "string" }
          }
        },
        "airTemperature": {
          "type": "object",
          "properties": {
            "type": { "type": "array", "items": { "type": "string" } },
            "description": { "type": "string" },
            "maxOverTime": {
              "type": "object",
              "properties": {
                "type": { "type": "array", "items": { "type": "string" } },
                "description": { "type": "string" },
                "dataSchema": { "type": "string" },
                "unitCode": { "type": "string" },
                "unitText": { "type": "string" }
              }
            },
            "minOverTime": {
              "type": "object",
              "properties": {
                "type": { "type": "array", "items": { "type": "string" } },
                "description": { "type": "string" },
                "dataSchema": { "type": "string" },
                "unitCode": { "type": "string" },
                "unitText": { "type": "string" }
              }
            }
          }
        },
        "relativeHumidity": {
          "type": "object",
          "properties": {
            "type": { "type": "array", "items": { "type": "string" } },
            "description": { "type": "string" },
            "maxOverTime": {
              "type": "object",
              "properties": {
                "type": { "type": "array", "items": { "type": "string" } },
                "description": { "type": "string" },
                "dataSchema": { "type": "string" },
                "unitCode": { "type": "string" },
                "unitText": { "type": "string" }
              }
            },
            "minOverTime": {
              "type": "object",
              "properties": {
                "type": { "type": "array", "items": { "type": "string" } },
                "description": { "type": "string" },
                "dataSchema": { "type": "string" },
                "unitCode": { "type": "string" },
                "unitText": { "type": "string" }
              }
            }
          }
        },
        "observationDateTime": {
          "type": "object",
          "properties": {
            "type": { "type": "array", "items": { "type": "string" } },
            "description": { "type": "string" },
            "dataSchema": { "type": "string" }
          }
        }
      }
    },
    "dataSample": {
      "type": "object",
      "properties": {
        "districtCode": { "type": ["string", "number"] },
        "subDistrictCode": { "type": ["string", "number"] },
        "precipitation": { "type": "number" },
        "airTemperature": {
          "type": "object",
          "properties": {
            "maxOverTime": { "type": "number" },
            "minOverTime": { "type": "number" }
          }
        },
        "relativeHumidity": {
          "type": "object",
          "properties": {
            "maxOverTime": { "type": "number" },
            "minOverTime": { "type": "number" }
          }
        },
        "observationDateTime": { "type": "string", "format": "date-time" }
      }
    },
    "itemStatus": {
      "type": "string",
      "enum": ["ACTIVE", "INACTIVE"]
    },
    "itemCreatedAt": {
      "type": "string",
      "format": "date-time"
    },
    "@context": {
      "type": "string",
      "format": "uri"
    }
  },
  "additionalProperties": true
}